broomio/__init__.py
broomio/_syscalls.py
broomio/_util.py
broomio/_pool/__init__.py
broomio/_pool/_queue.py
broomio/_sock/__init__.py
broomio/_sock/_epoll.py
broomio/_task/__init__.py
broomio/_task/_deque.py
broomio/_time/__init__.py
broomio/_time/_heapq.py
broomio-0.5.190510.dist-info/LICENSE
broomio-0.5.190510.dist-info/METADATA
broomio-0.5.190510.dist-info/WHEEL
broomio-0.5.190510.dist-info/top_level.txt
broomio-0.5.190510.dist-info/RECORD
