Metadata-Version: 2.1
Name: broomio
Version: 0.5.190510
Summary: Fast AsyncIO Library
Home-page: https://github.com/triflesoft/broomio
Author: Roman Akopov
Author-email: adontz@gmail.com
License: LGPL
Platform: UNKNOWN
Classifier: Development Status :: 4 - Beta
Classifier: Environment :: Console
Classifier: Environment :: Web Environment
Classifier: Intended Audience :: Developers
Classifier: License :: OSI Approved :: GNU Lesser General Public License v3 (LGPLv3)
Classifier: Operating System :: OS Independent
Classifier: Programming Language :: Python :: 3.6
Classifier: Programming Language :: Python :: 3.7
Classifier: Programming Language :: Python :: 3.8
